xai_blockchain_sdk/__init__.py
xai_blockchain_sdk/client.py
xai_blockchain_sdk/exceptions.py
xai_blockchain_sdk/http_client.py
xai_blockchain_sdk/models.py
xai_blockchain_sdk/py.typed
xai_blockchain_sdk/clients/__init__.py
xai_blockchain_sdk/clients/ai_client.py
xai_blockchain_sdk/clients/blockchain_client.py
xai_blockchain_sdk/clients/governance_client.py
xai_blockchain_sdk/clients/mining_client.py
xai_blockchain_sdk/clients/trading_client.py
xai_blockchain_sdk/clients/transaction_client.py
xai_blockchain_sdk/clients/wallet_client.py
xai_blockchain_sdk-1.0.0.dist-info/licenses/LICENSE
xai_blockchain_sdk-1.0.0.dist-info/METADATA
xai_blockchain_sdk-1.0.0.dist-info/WHEEL
xai_blockchain_sdk-1.0.0.dist-info/top_level.txt
xai_blockchain_sdk-1.0.0.dist-info/RECORD
