Metadata-Version: 2.4
Name: xai-blockchain-sdk
Version: 1.0.0
Summary: Python SDK for XAI Blockchain - AI compute pooling and governance
Author-email: XAI Blockchain <info@xaiblockchain.com>
Maintainer-email: XAI Blockchain <info@xaiblockchain.com>
License-Expression: Apache-2.0
Project-URL: Homepage, https://xaiblockchain.com
Project-URL: Documentation, https://docs.xaiblockchain.com
Project-URL: Repository, https://github.com/xai-blockchain/xai
Project-URL: Bug Tracker, https://github.com/xai-blockchain/xai/issues
Project-URL: Changelog, https://github.com/xai-blockchain/xai/blob/main/sdk/python/CHANGELOG.md
Keywords: blockchain,xai,sdk,cryptocurrency,ai-compute,governance,web3,decentralized
Classifier: Development Status :: 4 - Beta
Classifier: Intended Audience :: Developers
Classifier: Operating System :: OS Independent
Classifier: Programming Language :: Python :: 3
Classifier: Programming Language :: Python :: 3.9
Classifier: Programming Language :: Python :: 3.10
Classifier: Programming Language :: Python :: 3.11
Classifier: Programming Language :: Python :: 3.12
Classifier: Topic :: Software Development :: Libraries :: Python Modules
Classifier: Topic :: Internet :: WWW/HTTP
Classifier: Topic :: Security :: Cryptography
Requires-Python: >=3.9
License-File: LICENSE
Requires-Dist: requests>=2.28.0
Requires-Dist: urllib3>=1.26.0
Provides-Extra: dev
Requires-Dist: pytest>=7.0.0; extra == "dev"
Requires-Dist: pytest-cov>=4.0.0; extra == "dev"
Requires-Dist: black>=23.0.0; extra == "dev"
Requires-Dist: mypy>=1.0.0; extra == "dev"
Requires-Dist: types-requests>=2.28.0; extra == "dev"
Requires-Dist: ruff>=0.1.0; extra == "dev"
Dynamic: license-file
